<?xml version="1.0" encoding="utf-8" ?><dwsync><file name="ajax.html" server="23.239.30.92//public_html/" local="3510337666" remote="3509495940" Dst="-1" /><file name="api.html" server="23.239.30.92//public_html/" local="3510337666" remote="3509495940" Dst="-1" /><file name="appendto.html" server="23.239.30.92//public_html/" local="3510337666" remote="3509495940" Dst="-1" /><file name="divreplace.html" server="23.239.30.92//public_html/" local="3510337666" remote="3509495940" Dst="-1" /><file name="datafiltering.html" server="23.239.30.92//public_html/" local="3510337666" remote="3509495940" Dst="-1" /><file name="index.html" server="23.239.30.92//public_html/" local="3510337666" remote="3509495940" Dst="-1" /><file name="inlineall.html" server="23.239.30.92//public_html/" local="3510337667" remote="3509495940" Dst="-1" /><file name="inlinebycode.html" server="23.239.30.92//public_html/" local="3510337667" remote="3509495940" Dst="-1" /><file name="inlinetextarea.html" server="23.239.30.92//public_html/" local="3510337667" remote="3509495940" Dst="-1" /><file name="jquery.html" server="23.239.30.92//public_html/" local="3510337667" remote="3509495940" Dst="-1" /><file name="readonly.html" server="23.239.30.92//public_html/" local="3510337668" remote="3509495940" Dst="-1" /><file name="replacebyclass.html" server="23.239.30.92//public_html/" local="3510337668" remote="3509495940" Dst="-1" /><file name="replacebycode.html" server="23.239.30.92//public_html/" local="3510337668" remote="3509495940" Dst="-1" /><file name="sample.css" server="23.239.30.92//public_html/" local="3510337668" remote="3509495940" Dst="-1" /><file name="sample.js" server="23.239.30.92//public_html/" local="3510337668" remote="3509495940" Dst="-1" /><file name="sample_posteddata.php" server="23.239.30.92//public_html/" local="3510337668" remote="3509495940" Dst="-1" /><file name="tabindex.html" server="23.239.30.92//public_html/" local="3510337668" remote="3509495940" Dst="-1" /><file name="uicolor.html" server="23.239.30.92//public_html/" local="3510337668" remote="3509495940" Dst="-1" /><file name="uilanguages.html" server="23.239.30.92//public_html/" local="3510337668" remote="3509495940" Dst="-1" /><file name="xhtmlstyle.html" server="23.239.30.92//public_html/" local="3510337669" remote="3509495940" Dst="-1" /></dwsync>